nomisma/contractapi/BankAbstract.py
nomisma/contractapi/BankRegistry.py
nomisma/contractapi/BankRegistryAbstract.py
nomisma/contractapi/__init__.py
nomisma/contractapi/asyncexec.py
nomisma/contractapi/meta.py
nomisma/contractapi/tryout.py
nomisma/contractapi/util.py
nomisma/contractapi/abi/Bank.json
nomisma/contractapi/abi/BankBorrow.json
nomisma/contractapi/abi/BankDateKeeper.json
nomisma/contractapi/abi/BankEventEmitter.json
nomisma/contractapi/abi/BankInitialise.json
nomisma/contractapi/abi/BankInvest.json
nomisma/contractapi/abi/BankRedeem.json
nomisma/contractapi/abi/BankRegistry.json
nomisma/contractapi/abi/BankStateGetters.json
nomisma/contractapi/abi/Resolver.json
nomisma/contractapi/abi/TokenManager.json
nomisma/contractapi/abi/TokenManagerRouter.json
nomisma/contractapi/abi/TokenValidator.json
nomisma/contractapi/testutil/CapitalStructureTestResource.py
nomisma/contractapi/testutil/FullERC20MockAbstract.py
nomisma/contractapi/testutil/TruffleContract.py
nomisma/contractapi/testutil/__init__.py
nomisma/contractapi/testutil/mockutil.py
nomisma/contractapi/testutil/mockabi/ExchangeConnectorMock.json
nomisma/contractapi/testutil/mockabi/FullERC20Mock.json
nomisma.contractapi-0.0.2.dist-info/LICENSE
nomisma.contractapi-0.0.2.dist-info/METADATA
nomisma.contractapi-0.0.2.dist-info/NOTICE
nomisma.contractapi-0.0.2.dist-info/WHEEL
nomisma.contractapi-0.0.2.dist-info/top_level.txt
nomisma.contractapi-0.0.2.dist-info/RECORD
