Metadata-Version: 2.1
Name: nomisma.contractapi
Version: 0.0.2
Summary: Python API wrappers for Nomisma contracts
Home-page: https://github.com/NomismaTech/ContractAPI
Author: NomismaTech
Author-email: mohammad.rezaei@nomisma.one
License: Apache-2.0
Platform: UNKNOWN
Classifier: License :: OSI Approved :: Apache Software License
Classifier: Programming Language :: Python :: 3.7
Requires-Dist: web3 (>=5.0.0b1)
